TGPhind/Parser.py
TGPhind/__init__.py
TGPhind/__main__.py
TGPhind-1.0.0.dist-info/METADATA
TGPhind-1.0.0.dist-info/WHEEL
TGPhind-1.0.0.dist-info/top_level.txt
TGPhind-1.0.0.dist-info/RECORD
