Metadata-Version: 2.1
Name: TGPhind
Version: 1.0.0
Summary: Search for articles by title, in telegra.ph and its mirrors.
Home-page: https://github.com/NIKDISSV-Forever/TGPhind
Author: Nikita (NIKDISSV)
Author-email: nikdissv@proton.me
Classifier: Development Status :: 5 - Production/Stable
Classifier: Programming Language :: Python :: 3.10
Classifier: License :: OSI Approved :: MIT License
Classifier: Operating System :: OS Independent
Requires-Python: >=3.8
